auto_all.py
auto_all-1.3.0.dist-info/LICENSE
auto_all-1.3.0.dist-info/METADATA
auto_all-1.3.0.dist-info/WHEEL
auto_all-1.3.0.dist-info/top_level.txt
auto_all-1.3.0.dist-info/RECORD
